smartloc/__init__.py
selenium_smart_locator-0.3.0.dist-info/LICENSE
selenium_smart_locator-0.3.0.dist-info/METADATA
selenium_smart_locator-0.3.0.dist-info/WHEEL
selenium_smart_locator-0.3.0.dist-info/top_level.txt
selenium_smart_locator-0.3.0.dist-info/RECORD
