Metadata-Version: 2.1
Name: selenium-smart-locator
Version: 0.3.0
Summary: A (somewhat) smart locator class for Selenium.
Home-page: https://github.com/RedHatQE/selenium-smart-locator
Author: Milan Falesnik
Author-email: mfalesni@redhat.com
Maintainer: Mike Shriver
Maintainer-email: mshriver@redhat.com
License: GPLv3
Keywords: locator,selenium
Classifier: License :: OSI Approved :: GNU General Public License v3 (GPLv3)
Classifier: Programming Language :: Python
Classifier: Programming Language :: Python :: 3
Classifier: Programming Language :: Python :: 3.8
Classifier: Topic :: Utilities
Classifier: Topic :: Software Development :: Libraries :: Python Modules
Classifier: Topic :: Software Development :: Quality Assurance
Classifier: Topic :: Software Development :: Testing
License-File: LICENSE
Requires-Dist: selenium
Provides-Extra: test
Requires-Dist: pre-commit ; extra == 'test'
Requires-Dist: pytest ; extra == 'test'
Requires-Dist: pytest-cov ; extra == 'test'
